prism.py
prism_plot-1.6.dist-info/LICENSE
prism_plot-1.6.dist-info/METADATA
prism_plot-1.6.dist-info/WHEEL
prism_plot-1.6.dist-info/top_level.txt
prism_plot-1.6.dist-info/RECORD
