Metadata-Version: 2.1
Name: prism-plot
Version: 1.6
Summary: An animated wrapping of Dan Foreman-Mackey's triangle.py.
Home-page: https://github.com/bfarr/prism
Author: Ben Farr
Author-email: bfarr@uoregon.edu
License: UNKNOWN
Platform: UNKNOWN
